PyLTSpice/Histogram.py
PyLTSpice/LTSteps.py
PyLTSpice/__init__.py
PyLTSpice/rawplot.py
PyLTSpice/run_server.py
PyLTSpice/client_server/__init__.py
PyLTSpice/client_server/sim_client.py
PyLTSpice/client_server/sim_server.py
PyLTSpice/client_server/srv_sim_runner.py
PyLTSpice/editor/__init__.py
PyLTSpice/editor/asc_editor.py
PyLTSpice/editor/spice_editor.py
PyLTSpice/log/__init__.py
PyLTSpice/log/logfile_data.py
PyLTSpice/log/ltsteps.py
PyLTSpice/log/semi_dev_op_reader.py
PyLTSpice/raw/__init__.py
PyLTSpice/raw/raw_classes.py
PyLTSpice/raw/raw_convert.py
PyLTSpice/raw/raw_read.py
PyLTSpice/raw/raw_write.py
PyLTSpice/sim/__init__.py
PyLTSpice/sim/ltspice_simulator.py
PyLTSpice/sim/process_callback.py
PyLTSpice/sim/sim_batch.py
PyLTSpice/sim/sim_runner.py
PyLTSpice/sim/sim_stepping.py
PyLTSpice/sim/tookit/montecarlo.py
PyLTSpice/sim/tookit/worst_case.py
PyLTSpice/utils/detect_encoding.py
PyLTSpice/utils/sweep_iterators.py
examples/ltsteps_example.py
examples/raw_plotting.py
examples/raw_read_example.py
examples/raw_write_example.py
examples/run_montecarlo.py
examples/run_worst_case.py
examples/sim_runner_asc_example.py
examples/sim_runner_callback_example.py
examples/sim_runner_callback_process_example.py
examples/sim_runner_example.py
examples/sim_stepper_example.py
examples/spice_editor_example.py
examples/sub_circuit_asc_edits.py
pyltspice-5.4.4.dist-info/licenses/LICENSE
tests/batch_test.py
tests/batch_test2.py
tests/batch_test3.py
tests/batch_test4.py
tests/batch_test_with_abort.py
tests/fra_example.py
tests/ngspice_batch.py
tests/raw_plotting.py
tests/raw_write_tests.py
tests/raw_write_tools.py
tests/rc_example.py
tests/sim_server_example.py
tests/sketch.py
tests/test_ltsteps.py
tests/unittest/test_pyltspice.py
tests/unittest/sweep_iterators/sweep_iterators_unittest.py
unittests/sweep_iterators_unittest.py
unittests/test_asc_editor.py
unittests/test_pyltspice.py
pyltspice-5.4.4.dist-info/METADATA
pyltspice-5.4.4.dist-info/WHEEL
pyltspice-5.4.4.dist-info/top_level.txt
pyltspice-5.4.4.dist-info/RECORD
