Metadata-Version: 2.4
Name: PyLTSpice
Version: 5.4.4
Summary: A set of tools to Automate LTSpice simulations
Author-email: Nuno Brum <me@nunobrum.com>
License-Expression: GPL-3.0
Project-URL: Homepage, https://github.com/nunobrum/PyLTSpice
Project-URL: Bug Tracker, https://github.com/nunobrum/PyLTSpice/issues
Project-URL: Repository, https://github.com/nunobrum/PyLTSpice.git
Project-URL: Author, https://www.nunobrum.com/
Classifier: Programming Language :: Python :: 3
Classifier: Operating System :: OS Independent
Requires-Python: >=3.9
License-File: LICENSE
Requires-Dist: spicelib>=1.4.6
Dynamic: license-file
